{
	"id": "007-films",
	"title": "Marathon James Bond",
	"description": "Every James Bond film, including the two non-canon ones. A solo marathon I picked up after playing 007 First Light.",
	"source": "TMDB_MOVIE",
	"url": "https://en.wikipedia.org/wiki/List_of_James_Bond_films",
	"movies": [
		[646, "Dr. No"],
		[657, "From Russia with Love"],
		[658, "Goldfinger"],
		[660, "Thunderball"],
		[667, "You Only Live Twice"],
		[12208, "Casino Royale"],
		[668, "On Her Majesty's Secret Service"],
		[681, "Diamonds Are Forever"],
		[253, "Live and Let Die"],
		[682, "The Man with the Golden Gun"],
		[691, "The Spy Who Loved Me"],
		[698, "Moonraker"],
		[699, "For Your Eyes Only"],
		[700, "Octopussy"],
		[36670, "Never Say Never Again"],
		[707, "A View to a Kill"],
		[708, "The Living Daylights"],
		[709, "Licence to Kill"],
		[710, "GoldenEye"],
		[714, "Tomorrow Never Dies"],
		[36643, "The World Is Not Enough"],
		[36669, "Die Another Day"],
		[36557, "Casino Royale"],
		[10764, "Quantum of Solace"],
		[37724, "Skyfall"],
		[206647, "Spectre"],
		[370172, "No Time to Die"]
	]
}
